{
	"levels" : ["4","8","10","12","16","18","24","28","31","38"],
	"gems" : [
		{	"level" : "4",
			"links" : [
				"B,Frost Bomb [Tarkleigh]",
				"B,Arcane Surge [Nessa]",
				"G,Onslaught (Nessa/Wisdom | Scion Mule)",
				"",
				"B,Orb of Storms (Nessa/Wisdom)",
				"B,Elemental Proliferation",
				"",
				"B,Stormblast Mines",
				"",
				"B,Frostblink [Tarkleigh]"
			]
		},
		{	"level" : "8",
			"links" : [
				"B,Orb of Storms",
				"B,Added Lightning [Nessa]",
				"B,Elemental Proliferation",
				"",
				"B,Frost Bomb",
				"G,Onslaught",
				"",
				"B,Stormblast Mines",
				"B,Arcane Surge (lvl 1)",
				"B,Added Lightning [Nessa/Transmute]",
				"",
				"B,Frostblink"
			]
		},
		{	"level" : "10",
			"links" : [
				"B,Orb of Storms",
				"B,Added Lightning",
				"B,Elemental Proliferation",
				"",
				"B,Frost Bomb",
				"G,Onslaught",
				"",
				"B,Stormblast Mines",
				"B,Arcane Surge (lvl 1)",
				"B,Added Lightning",
				"",
				"B,Flame Dash [Tarkleigh]"
			]
		},
		{	"level" : "12",
			"links" : [
				"B,Orb of Storms",
				"B,Elemental Proliferation (swap out Added Light)",
				"G,Onslaught",
				"",
				"B,Arc [Nessa]",
				"B,Arcane Surge",
				"",
				"B,Stormblast Mines",
				"B,Arcane Surge (lvl 1)",
				"B,Added Lightning",
				"",
				"B,Flame Dash",
				"",
				"{{ Offhand }}",
				"B,Frost Bomb"
			]
		},
		{	"level" : "16",
			"links" : [
				"B,Orb of Storms",
				"B,Elemental Proliferation",
				"G,Onslaught",
				"",
				"B,Wave of Conviction [Silk | Alteration]",
				"B,Added Lightning",
				"",
				"B,Herald of Thunder [Alteration]",
				"G,Herald of Ice [Alteration]",
				"",
				"B,Flame Dash",
				"B,Arcane Surge",
				"",
				"B,Clarity lvl 1",
				"",
				"{{ Offhand }}",
				"B,Frost Bomb",
				"B,Storm Brand [Alteration]"
			]
		},
		{	"level" : "18",
			"links" : [
				"B,Orb of Storms",
				"B,Elemental Proliferation",
				"G,Onslaught",
				"",
				"B,Wave of Conviction",
				"B,Faster Casting [Reward | Alteration]",
				"B,Physical to Lightning [Reward | Alteration]",
				"",
				"B,Herald of Thunder",
				"G,Herald of Ice",
				"",
				"B,Flame Dash",
				"B,Arcane Surge",
				"B,Faster Casting [Reward | Alteration]",
				"",
				"B,Clarity lvl 1",
				"",
				"{{ Offhand }}",
				"B,Frost Bomb",
				"B,Storm Brand",
				"B,Vaal/Cold Snap [Alteration]",
				"B,Added Lightning"
			]
		},
		{	"level" : "24",
			"links" : [
				"B,Orb of Storms",
				"B,Elemental Proliferation",
				"G,Onslaught",
				"",
				"B,Wave of Conviction",
				"B,Faster Casting",
				"B,Physical to Lightning",
				"",
				"B,Herald of Thunder",
				"G,Herald of Ice",
				"",
				"B,Flame Dash",
				"B,Arcane Surge",
				"B,Faster Casting",
				"",
				"B,Clarity lvl 1",
				"",
				"{{ Offhand }}",
				"B,Frost Bomb",
				"B,Storm Brand",
				"B,Vaal/Cold Snap",
				"B,Conductivity [Alteration]",
				"B,Malevolence [Alteration]",
				"B,Discipline [Alteration]"
			]
		},
		{	"level" : "28",
			"links" : [
				"B,Orb of Storms",
				"B,Elemental Proliferation",
				"G,Onslaught",
				"",
				"B,Wave of Conviction",
				"B,Faster Casting",
				"B,Physical to Lightning",
				"B,Added Lightning",
				"",
				"B,Lightning Spire [Chance]",
				"B,Elemental Focus [Alteration]",
				"G,Trap and Mine Damage [Alteration]",
				"",
				"B,Herald of Thunder",
				"G,Herald of Ice",
				"G,Onslaught [Wisdom | Siosa]",
				"",
				"B,Flame Dash",
				"B,Arcane Surge",
				"B,Faster Casting",
				"",
				"B,Clarity lvl 1",
				"",
				"{{ Offhand }}",
				"B,Frost Bomb",
				"B,Vortex [Chance]",
				"B,Vaal/Cold Snap",
				"B,Conductivity",
				"B,Malevolence",
				"B,Discipline"
			]
		},
		{	"level" : "31",
			"links" : [
				"B,Orb of Storms",
				"B,Elemental Proliferation",
				"G,Onslaught",
				"G,Ice Bite [Chance]",
				"",
				"B,Wave of Conviction",
				"B,Faster Casting",
				"B,Physical to Lightning",
				"B,Added Lightning",
				"",
				"B,Lightning Spire",
				"B,Elemental Focus",
				"G,Trap and Mine Damage",
				"G,Advanced Traps [Chance]",
				"",
				"B,Herald of Thunder",
				"G,Herald of Ice",
				"G,Onslaught",
				"",
				"B,Flame Dash",
				"B,Arcane Surge",
				"B,Faster Casting",
				"",
				"B,Clarity lvl 1",
				"",
				"{{ Offhand }}",
				"B,Frost Bomb",
				"B,Vortex",
				"B,Vaal/Cold Snap",
				"B,Conductivity",
				"B,Malevolence",
				"B,Discipline"
			]
		},
		{	"level" : "38",
			"links" : [
				"B,Orb of Storms",
				"B,Elemental Proliferation",
				"G,Chain [Alch]",
				"G,Ice Bite",
				"",
				"B,Wave of Conviction",
				"B,Faster Casting",
				"B,Physical to Lightning",
				"B,Added Lightning",
				"",
				"B,Lightning Spire",
				"B,Elemental Focus",
				"G,Trap and Mine Damage",
				"G,Advanced Traps",
				"",
				"B,Curse on Hit [Alch]",
				"B,Conductivity",
				"G,Herald of Ice",
				"G,Onslaught",
				"",
				"B,Flame Dash",
				"B,Arcane Surge",
				"B,Faster Casting",
				"",
				"B,Clarity lvl 1",
				"",
				"{{ Offhand }}",
				"B,Frost Bomb",
				"B,Vortex",
				"B,Vaal/Cold Snap",
				"B,Conductivity",
				"B,Malevolence",
				"B,Discipline"
			]
		}
	]
}